extract_sfm/.DS_Store
extract_sfm/__init__.py
extract_sfm/ann_json.py
extract_sfm/config.py
extract_sfm/data.py
extract_sfm/eval.py
extract_sfm/fast_parse.py
extract_sfm/model.h5
extract_sfm/ne_def.py
extract_sfm/ner.py
extract_sfm/nn_eval.py
extract_sfm/parse.py
extract_sfm/parse_script.py
extract_sfm/path.py
extract_sfm/patterns.p
extract_sfm/pipeline.py
extract_sfm/pred.py
extract_sfm/process.py
extract_sfm/relation_dep.py
extract_sfm/relation_nn.py
extract_sfm/tf_metrics.py
extract_sfm/train.py
extract_sfm/train_re.py
extract_sfm/SFM_STARTER/glove.npz
extract_sfm/SFM_STARTER/test.tags.txt
extract_sfm/SFM_STARTER/test.words.txt
extract_sfm/SFM_STARTER/train.tags.txt
extract_sfm/SFM_STARTER/train.words.txt
extract_sfm/SFM_STARTER/valid.tags.txt
extract_sfm/SFM_STARTER/valid.words.txt
extract_sfm/SFM_STARTER/vocab.chars.txt
extract_sfm/SFM_STARTER/vocab.tags.txt
extract_sfm/SFM_STARTER/vocab.words.txt
extract_sfm/jPTDP/License.txt
extract_sfm/jPTDP/README.md
extract_sfm/jPTDP/decoder.py
extract_sfm/jPTDP/decoder.pyc
extract_sfm/jPTDP/fast_parse.py
extract_sfm/jPTDP/jPTDP.py
extract_sfm/jPTDP/learner.py
extract_sfm/jPTDP/learner.pyc
extract_sfm/jPTDP/mnnl.py
extract_sfm/jPTDP/mnnl.pyc
extract_sfm/jPTDP/utils.py
extract_sfm/jPTDP/utils.pyc
extract_sfm/jPTDP/sample/dev.conllu
extract_sfm/jPTDP/sample/model256
extract_sfm/jPTDP/sample/model256.params
extract_sfm/jPTDP/sample/test
extract_sfm/jPTDP/sample/train.conllu
extract_sfm/jPTDP/utils/conll17_ud_eval.py
extract_sfm/jPTDP/utils/converter.py
extract_sfm/jPTDP/utils/swapper.py
extract_sfm/results/main.log
extract_sfm/results/params.json
extract_sfm/results/model/checkpoint
extract_sfm/results/model/graph.pbtxt
extract_sfm/results/model/model.ckpt-12305.data-00000-of-00001
extract_sfm/results/model/model.ckpt-12305.index
extract_sfm/results/model/model.ckpt-12305.meta
extract_sfm-2.0.dist-info/LICENSE
extract_sfm-2.0.dist-info/METADATA
extract_sfm-2.0.dist-info/WHEEL
extract_sfm-2.0.dist-info/top_level.txt
extract_sfm-2.0.dist-info/RECORD
