Metadata-Version: 2.1
Name: extract-sfm
Version: 2.0
Summary: Knowledge Graph Extraction for SFM dataset
Home-page: https://github.com/Panmani/KGE
Author: Yueen Ma
License: UNKNOWN
Platform: UNKNOWN
Classifier: Programming Language :: Python :: 3
Classifier: License :: OSI Approved :: MIT License
Classifier: Operating System :: OS Independent
Requires-Python: >=3.6
Requires-Dist: numpy
Requires-Dist: tensorflow
Requires-Dist: tensorflow-addons
Requires-Dist: spacy
Requires-Dist: dynet
Requires-Dist: pathlib
